errorcode_generator.py
errorcode_generator-0.2.0.dist-info/LICENSE
errorcode_generator-0.2.0.dist-info/METADATA
errorcode_generator-0.2.0.dist-info/WHEEL
errorcode_generator-0.2.0.dist-info/entry_points.txt
errorcode_generator-0.2.0.dist-info/RECORD
