Metadata-Version: 2.1
Name: errorcode-generator
Version: 0.2.0
Summary: 根据模板文件生成各种错误码文本格式
License: BSD-4-Clause
Author: riag
Author-email: riag@163.com
Requires-Python: >=3.7,<4.0
Classifier: License :: Other/Proprietary License
Classifier: Programming Language :: Python :: 3
Classifier: Programming Language :: Python :: 3.7
Classifier: Programming Language :: Python :: 3.8
Classifier: Programming Language :: Python :: 3.9
Classifier: Programming Language :: Python :: 3.10
Classifier: Programming Language :: Python :: 3.11
Requires-Dist: jinja2 (>=3.1.2,<4.0.0)
Requires-Dist: typing (>=3.7.4,<4.0.0)
